numdifftools/__init__.py
numdifftools/_find_default_scale.py
numdifftools/core.py
numdifftools/example_functions.py
numdifftools/extrapolation.py
numdifftools/finite_difference.py
numdifftools/fornberg.py
numdifftools/info.py
numdifftools/license.py
numdifftools/limits.py
numdifftools/multicomplex.py
numdifftools/nd_algopy.py
numdifftools/nd_scipy.py
numdifftools/nd_statsmodels.py
numdifftools/profile_numdifftools.py
numdifftools/profiletools.py
numdifftools/run_benchmark.py
numdifftools/step_generators.py
numdifftools/testing.py
numdifftools/tests/__init__.py
numdifftools/tests/hamiltonian.py
numdifftools/tests/test_example_functions.py
numdifftools/tests/test_extrapolation.py
numdifftools/tests/test_fornberg.py
numdifftools/tests/test_limits.py
numdifftools/tests/test_multicomplex.py
numdifftools/tests/test_nd_algopy.py
numdifftools/tests/test_nd_scipy.py
numdifftools/tests/test_numdifftools.py
numdifftools/tests/test_scripts.py
numdifftools/tests/test_step_generators.py
numdifftools/tests/test_wprofiletools.py
numdifftools-0.9.40.dist-info/LICENSE.txt
numdifftools-0.9.40.dist-info/METADATA
numdifftools-0.9.40.dist-info/WHEEL
numdifftools-0.9.40.dist-info/top_level.txt
numdifftools-0.9.40.dist-info/RECORD
