Metadata-Version: 2.1
Name: numdifftools
Version: 0.9.40
Summary: Solves automatic numerical differentiation problems in one or more variables.
Home-page: https://github.com/pbrod/numdifftools
Author: Per A. Brodtkorb
Author-email: per.andreas.brodtkorb@gmail.com
License: new BSD
Platform: any
Classifier: Development Status :: 4 - Beta
Classifier: Programming Language :: Python
Classifier: Programming Language :: Python :: 2.7
Classifier: Programming Language :: Python :: 3.6
Classifier: Programming Language :: Python :: 3.7
Classifier: Programming Language :: Python :: 3.8
Classifier: Programming Language :: Python :: 3.9
Classifier: Environment :: Console
Classifier: Intended Audience :: Education
Classifier: Intended Audience :: Science/Research
Classifier: License :: OSI Approved :: BSD License
Classifier: Operating System :: OS Independent
Classifier: Operating System :: POSIX :: Linux
Classifier: Operating System :: Unix
Classifier: Operating System :: MacOS
Classifier: Operating System :: Microsoft :: Windows
Classifier: Topic :: Scientific/Engineering :: Mathematics
Provides-Extra: build_sphinx
